datastructspawner/__init__.py
datastructspawner/structs.py
datastructspawner-0.0.2.dist-info/LICENSE
datastructspawner-0.0.2.dist-info/METADATA
datastructspawner-0.0.2.dist-info/WHEEL
datastructspawner-0.0.2.dist-info/top_level.txt
datastructspawner-0.0.2.dist-info/RECORD
