Metadata-Version: 2.1
Name: datastructspawner
Version: 0.0.2
Summary: Gerador de estruturas de dados
Author: Joao Neto e Lindaiely Rodrigues
Author-email: joaonetoprivado2001@ufpi.edu.br
License: MIT License
Keywords: estrutura de dados
License-File: LICENSE
